pandas_timeinterval/__init__.py
pandas_timeinterval/intervals.py
pandas_timeinterval-2025.8.1.dist-info/licenses/LICENSE
pandas_timeinterval-2025.8.1.dist-info/METADATA
pandas_timeinterval-2025.8.1.dist-info/WHEEL
pandas_timeinterval-2025.8.1.dist-info/top_level.txt
pandas_timeinterval-2025.8.1.dist-info/RECORD
