Metadata-Version: 2.4
Name: pandas_timeinterval
Version: 2025.8.1
Summary: A package to trim datetime indexed DataFrames and Series in pandas.
Author-email: Jarrett Bullion <jjrreett@gmail.com>
License: MIT License
Project-URL: Homepage, https://github.com/jjrreett/pandas-timeinterval
Keywords: pandas,datetime,intervals,dataframes
Classifier: Programming Language :: Python :: 3
Classifier: License :: OSI Approved :: MIT License
Classifier: Operating System :: OS Independent
Requires-Python: >=3.7
License-File: LICENSE
Requires-Dist: pandas>=1.0
Provides-Extra: dev
Requires-Dist: ruff; extra == "dev"
Requires-Dist: pytest; extra == "dev"
Dynamic: license-file
